{
  "name": "bs-calendar",
  "type": "registry:ui",
  "title": "Bikram Sambat Calendar (Native)",
  "description": "NativeWind Bikram Sambat calendar for React Native / Expo.",
  "dependencies": [
    "clsx",
    "tailwind-merge",
    "lucide-react-native"
  ],
  "files": [
    {
      "path": "registry/native/files/components/ui/bs-calendar.tsx",
      "type": "registry:ui",
      "target": "components/ui/bs-calendar.tsx"
    },
    {
      "path": "registry/native/files/components/ui/bs-calendar.android.tsx",
      "type": "registry:ui",
      "target": "components/ui/bs-calendar.android.tsx"
    },
    {
      "path": "registry/native/files/lib/bs-day-picker/bs-day-picker.tsx",
      "type": "registry:lib",
      "target": "lib/bs-day-picker/bs-day-picker.tsx"
    },
    {
      "path": "registry/native/files/lib/bs-day-picker/types.ts",
      "type": "registry:lib",
      "target": "lib/bs-day-picker/types.ts"
    },
    {
      "path": "registry/native/files/lib/bs-day-picker/constants.ts",
      "type": "registry:lib",
      "target": "lib/bs-day-picker/constants.ts"
    },
    {
      "path": "registry/native/files/lib/bs-day-picker/formatters.ts",
      "type": "registry:lib",
      "target": "lib/bs-day-picker/formatters.ts"
    },
    {
      "path": "registry/native/files/lib/bs-day-picker/pattern.ts",
      "type": "registry:lib",
      "target": "lib/bs-day-picker/pattern.ts"
    },
    {
      "path": "registry/native/files/lib/bs-day-picker/navigation.ts",
      "type": "registry:lib",
      "target": "lib/bs-day-picker/navigation.ts"
    },
    {
      "path": "registry/native/files/lib/bs-day-picker/calendar-grid.ts",
      "type": "registry:lib",
      "target": "lib/bs-day-picker/calendar-grid.ts"
    },
    {
      "path": "registry/native/files/lib/bs-day-picker/selection.ts",
      "type": "registry:lib",
      "target": "lib/bs-day-picker/selection.ts"
    },
    {
      "path": "registry/native/files/lib/bs-day-picker/use-bs-calendar.ts",
      "type": "registry:lib",
      "target": "lib/bs-day-picker/use-bs-calendar.ts"
    },
    {
      "path": "registry/native/files/lib/bs-day-picker/index.ts",
      "type": "registry:lib",
      "target": "lib/bs-day-picker/index.ts"
    },
    {
      "path": "registry/native/files/lib/bs-day-picker/data/bs-calendar.json",
      "type": "registry:lib",
      "target": "lib/bs-day-picker/data/bs-calendar.json"
    }
  ]
}